scholarai/__init__.py
scholarai/_base_client.py
scholarai/_client.py
scholarai/_compat.py
scholarai/_constants.py
scholarai/_exceptions.py
scholarai/_files.py
scholarai/_models.py
scholarai/_qs.py
scholarai/_resource.py
scholarai/_response.py
scholarai/_streaming.py
scholarai/_types.py
scholarai/_version.py
scholarai/py.typed
scholarai/_utils/__init__.py
scholarai/_utils/_logs.py
scholarai/_utils/_proxy.py
scholarai/_utils/_reflection.py
scholarai/_utils/_resources_proxy.py
scholarai/_utils/_streams.py
scholarai/_utils/_sync.py
scholarai/_utils/_transform.py
scholarai/_utils/_typing.py
scholarai/_utils/_utils.py
scholarai/lib/.keep
scholarai/resources/__init__.py
scholarai/resources/abstracts.py
scholarai/resources/add_to_project.py
scholarai/resources/analyze_project.py
scholarai/resources/chat.py
scholarai/resources/create_project.py
scholarai/resources/fulltext.py
scholarai/resources/patents.py
scholarai/resources/question.py
scholarai/resources/save_citation.py
scholarai/types/__init__.py
scholarai/types/abstract_search_params.py
scholarai/types/abstract_search_response.py
scholarai/types/add_to_project_create_params.py
scholarai/types/add_to_project_create_response.py
scholarai/types/add_to_project_retrieve_params.py
scholarai/types/add_to_project_retrieve_response.py
scholarai/types/analyze_project_batch_analyze_params.py
scholarai/types/analyze_project_batch_analyze_response.py
scholarai/types/chat_create_completion_params.py
scholarai/types/create_project_create_params.py
scholarai/types/fulltext_retrieve_params.py
scholarai/types/paper_content.py
scholarai/types/paper_metadata.py
scholarai/types/patent_list_params.py
scholarai/types/patent_list_response.py
scholarai/types/question_ask_params.py
scholarai/types/save_citation_retrieve_params.py
scholarai/types/save_citation_retrieve_response.py
scholarai-0.0.1a1.dist-info/METADATA
scholarai-0.0.1a1.dist-info/WHEEL
scholarai-0.0.1a1.dist-info/licenses/LICENSE
scholarai-0.0.1a1.dist-info/RECORD
